{
  "settings": {
    "migrated": true,
    "iconPacksPath": ".obsidian/plugins/obsidian-icon-folder/icons",
    "fontSize": 16,
    "emojiStyle": "none",
    "iconColor": null,
    "recentlyUsedIcons": [
      "SiVisualstudiocode",
      "SiPlatformdotsh",
      "SiJavascript",
      "SiHtml5",
      "SiGit"
    ],
    "recentlyUsedIconsSize": 5,
    "rules": [],
    "extraMargin": {
      "top": 0,
      "right": 4,
      "bottom": 0,
      "left": 0
    },
    "iconInTabsEnabled": false
  },
  "Github": "SiGit",
  "HTML CSS": "SiHtml5",
  "Javascript": "SiJavascript",
  "Miscellaneous": "SiPlatformdotsh",
  "VScode": "SiVisualstudiocode"
}